dropmqttapi/__init__.py
dropmqttapi/discovery.py
dropmqttapi/mqttapi.py
dropmqttapi-1.0.2.dist-info/LICENSE
dropmqttapi-1.0.2.dist-info/METADATA
dropmqttapi-1.0.2.dist-info/WHEEL
dropmqttapi-1.0.2.dist-info/top_level.txt
dropmqttapi-1.0.2.dist-info/RECORD
