Metadata-Version: 2.1
Name: dropmqttapi
Version: 1.0.2
Summary: MQTT API for DROP water management products
Author-email: Patrick Frazer <pfrazer@chandlersystemsinc.com>
License: MIT License
Project-URL: Homepage, https://github.com/ChandlerSystems/dropmqttapi
Keywords: drop,mqtt,api
Classifier: License :: OSI Approved :: MIT License
Classifier: Programming Language :: Python
Classifier: Programming Language :: Python :: 3
Requires-Python: >=3.11
License-File: LICENSE
